queryish/__init__.py
queryish/rest.py
queryish-0.3.dist-info/licenses/LICENSE
queryish-0.3.dist-info/METADATA
queryish-0.3.dist-info/WHEEL
queryish-0.3.dist-info/top_level.txt
queryish-0.3.dist-info/RECORD
