Metadata-Version: 2.4
Name: queryish
Version: 0.3
Summary: A library for constructing queries on arbitrary data sources following Django's QuerySet API
Home-page: https://github.com/wagtail/queryish
Author: Matthew Westcott
Author-email: matthew.westcott@torchbox.com
License: BSD-3-Clause
Classifier: Development Status :: 3 - Alpha
Classifier: Intended Audience :: Developers
Classifier: Operating System :: OS Independent
Classifier: Programming Language :: Python
Classifier: Programming Language :: Python :: 3
Classifier: Programming Language :: Python :: 3 :: Only
Classifier: Framework :: Django
Requires-Python: >=3.7
License-File: LICENSE
Requires-Dist: requests<3.0,>=2.28
Provides-Extra: testing
Requires-Dist: responses<1.0,>=0.23; extra == "testing"
Requires-Dist: django>=4.2; extra == "testing"
Dynamic: author
Dynamic: author-email
Dynamic: classifier
Dynamic: description
Dynamic: description-content-type
Dynamic: home-page
Dynamic: license
Dynamic: license-file
Dynamic: provides-extra
Dynamic: requires-dist
Dynamic: requires-python
Dynamic: summary
